odoo/addons/base_report_to_printer_mail/README.rst
odoo/addons/base_report_to_printer_mail/__init__.py
odoo/addons/base_report_to_printer_mail/__manifest__.py
odoo/addons/base_report_to_printer_mail/i18n/base_report_to_printer_mail.pot
odoo/addons/base_report_to_printer_mail/i18n/it.po
odoo/addons/base_report_to_printer_mail/i18n/sv.po
odoo/addons/base_report_to_printer_mail/models/__init__.py
odoo/addons/base_report_to_printer_mail/models/mail_template.py
odoo/addons/base_report_to_printer_mail/readme/CONTRIBUTORS.rst
odoo/addons/base_report_to_printer_mail/readme/DESCRIPTION.rst
odoo/addons/base_report_to_printer_mail/static/description/icon.png
odoo/addons/base_report_to_printer_mail/static/description/index.html
odoo/addons/base_report_to_printer_mail/tests/__init__.py
odoo/addons/base_report_to_printer_mail/tests/test_mail.py
odoo14_addon_base_report_to_printer_mail-14.0.1.0.1.dev8.dist-info/METADATA
odoo14_addon_base_report_to_printer_mail-14.0.1.0.1.dev8.dist-info/WHEEL
odoo14_addon_base_report_to_printer_mail-14.0.1.0.1.dev8.dist-info/top_level.txt
odoo14_addon_base_report_to_printer_mail-14.0.1.0.1.dev8.dist-info/RECORD
